kamodo_core/__init__.py
kamodo_core/kamodo.py
kamodo_core/plotting.py
kamodo_core/test_kamodo.py
kamodo_core/test_plotting.py
kamodo_core/test_utils.py
kamodo_core/util.py
kamodo_core/cli/__init__.py
kamodo_core/cli/api.py
kamodo_core/cli/gui.py
kamodo_core/cli/main.py
kamodo_core/cli/assets/Kamodo-black.png
kamodo_core/cli/assets/bWLwgP.css
kamodo_core/cli/assets/clientside.js
kamodo_core/cli/assets/favicon.ico
kamodo_core/cli/conf/config.yaml
kamodo_core/cli/conf/kamodo.yaml
kamodo_core/cli/conf/model/test.yaml
kamodo_core/cli/conf/model/tiegcm.yaml
kamodo_core-1.0.11.dist-info/LICENSE
kamodo_core-1.0.11.dist-info/METADATA
kamodo_core-1.0.11.dist-info/WHEEL
kamodo_core-1.0.11.dist-info/entry_points.txt
kamodo_core-1.0.11.dist-info/top_level.txt
kamodo_core-1.0.11.dist-info/RECORD
